Workbook

Sheet Read Me
A1: Ayyappa Pooja Store - Data Workbook
A3: Products: product list (names in 6 languages). Add a row for each new product.
A4: Lots: one row per stock arrival. Lot_Expenses_Total and stock columns fill themselves in.
A5: Expenses: extra costs for a lot (transport, packing...). Use the same Lot_ID as the Lots row.
A6: Sales: one row per FIFO slice of a sale. The website writes these rows; do not type sales here.
A7: Overhead: monthly running costs. Month is YYYY-MM.
A8: Quotes: quotations made on the website. Change Status as they progress.
A9: Stock: automatic. Do not type here.
A11: Keep sheet names and column headings exactly as they are.
A13: ഉൽപ്പന്നങ്ങൾ: ഓരോ പുതിയ ഉൽപ്പന്നത്തിനും ഒരു വരി ചേർക്കുക.
A14: ലോട്ടുകൾ: പുതിയ സ്റ്റോക്ക് വരുമ്പോൾ ഒരു വരി ചേർക്കുക.
A15: ചെലവുകൾ: ലോട്ടിനുള്ള അധിക ചെലവുകൾ. അതേ Lot_ID ഉപയോഗിക്കുക.
A16: സ്റ്റോക്ക്: ബാക്കിയുള്ളവയുടെ പട്ടിക. ഇതിൽ ഒന്നും ടൈപ്പ് ചെയ്യേണ്ടതില്ല.

Sheet Products
A1: Product_ID | B1: Name_Malayalam | C1: Name_English | D1: Name_Tamil | E1: Name_Kannada | F1: Name_Telugu | G1: Name_Hindi | H1: Category | I1: Default_Selling_Price | J1: Image_Folder
A2: P001 | B2: പിത്തള വിളക്ക് | C2: Brass Lamp | D2: பித்தளை விளக்கு | E2: ಹಿತ್ತಾಳೆ ದೀಪ | F2: ఇత్తడి దీపం | G2: पीतल का दीया | H2: Pooja Items | I2: 200 | J2: P001_Brass_Lamp
A3: P002 | B3: അഗർബത്തി | C3: Agarbatti | D3: அகர்பத்தி | E3: ಅಗರ್ಬತ್ತಿ | F3: అగరబత్తి | G3: अगरबत्ती | H3: Incense | I3: 15 | J3: P002_Agarbatti
A4: P003 | B4: പൂജാ താലം | C4: Pooja Thali | D4: பூஜை தட்டு | E4: ಪೂಜಾ ತಟ್ಟೆ | F4: పూజా తాళం | G4: पूजा थाली | H4: Pooja Items | I4: 250 | J4: P003_Pooja_Thali
A5: P004 | B5: കുങ്കുമം | C5: Kumkum | D5: குங்குமம் | E5: ಕುಂಕುಮ | F5: కుంకుమ | G5: कुंकुम | H5: Pooja Items | I5: 30 | J5: P004_Kumkum
A6: P005 | B6: കർപ്പൂരം | C6: Camphor | D6: கற்பூரம் | E6: ಕರ್ಪೂರ | F6: కర్పూరం | G6: कपूर | H6: Pooja Items | I6: 20 | J6: P005_Camphor
A7: P006 | B7: പിത്തള വിഗ്രഹം | C7: Brass Idol | D7: பித்தளை சிலை | E7: ಹಿತ್ತಾಳೆ ವಿಗ್ರಹ | F7: ఇత్తడి విగ్రహం | G7: पीतल की मूर्ति | H7: Idols | I7: 500 | J7: P006_Brass_Idol
A8: K001 | B8: ഉപ്പേരി | C8: Banana Chips | D8: வாழைக்காய் சிப்ஸ் | E8: ಬಾಳೆಕಾಯಿ ಚಿಪ್ಸ್ | F8: అరటికాయ చిప్స్ | G8: केले के चिप्स | H8: Kerala Snacks | I8: 80 | J8: K001_Banana_Chips
A9: K002 | B9: മിക്സ്ചർ | C9: Mixture | D9: மிக்சர் | E9: ಮಿಕ್ಸ್ಚರ್ | F9: మిక్చర్ | G9: मिक्सचर | H9: Kerala Snacks | I9: 120 | J9: K002_Mixture
A10: K003 | B10: മുറുക്ക് | C10: Murukku | D10: முறுக்கு | E10: ಮುರುಕ್ಕು | F10: మురుక్కు | G10: मुरुक्कु | H10: Kerala Snacks | I10: 100 | J10: K003_Murukku
A11: K004 | B11: അച്ചപ്പം | C11: Achappam | D11: அச்சப்பம் | E11: ಅಚ್ಚಪ್ಪಂ | F11: అచ్చప్పం | G11: अच्चप्पम | H11: Kerala Snacks | I11: 90 | J11: K004_Achappam
A12: K005 | B12: ചക്ക ചിപ്സ് | C12: Jackfruit Chips | D12: பலா சிப்ஸ் | E12: ಹಲಸಿನ ಹಣ್ಣಿನ ಚಿಪ್ಸ್ | F12: పనస చిప్స్ | G12: कटहल के चिप्स | H12: Kerala Snacks | I12: 150 | J12: K005_Jackfruit_Chips
A13: K006 | B13: കപ്പ ചിപ്സ് | C13: Tapioca Chips | D13: மரவள்ளிக்கிழங்கு சிப்ஸ் | E13: ಮರಗೆಣಸು ಚಿಪ್ಸ್ | F13: కర్రపెండలం చిప్స్ | G13: कसावा चिप्स | H13: Kerala Snacks | I13: 70 | J13: K006_Tapioca_Chips
... A17: K010 | B17: ശർക്കര | C17: Jaggery | D17: வெல்லம் | E17: ಬೆಲ್ಲ | F17: బెల్లం | G17: गुड़ | H17: Kerala Products | I17: 60 | J17: K010_Jaggery

Sheet Lots
A1: Lot_ID | B1: Product_ID | C1: Received_On | D1: Supplier | E1: Buy_Price_Unit | F1: Qty_Received | G1: Selling_Price_Unit | H1: Expense_Note | I1: Lot_Expenses_Total | J1: Qty_Sold | K1: Qty_Remaining | L1: Landed_Cost_Unit | M1: Status
I2: =IF(A2="","",SUMIFS(Expenses!D:D,Expenses!B:B,A2)) | J2: =IF(A2="","",SUMIFS(Sales!F:F,Sales!E:E,A2)) | K2: =IF(A2="","",F2-J2) | L2: =IF(A2="","",IF(F2=0,"",(E2*F2+I2)/F2)) | M2: =IF(A2="","",IF(K2<=0,"Sold Out","Active"))
I3: =IF(A3="","",SUMIFS(Expenses!D:D,Expenses!B:B,A3)) | J3: =IF(A3="","",SUMIFS(Sales!F:F,Sales!E:E,A3)) | K3: =IF(A3="","",F3-J3) | L3: =IF(A3="","",IF(F3=0,"",(E3*F3+I3)/F3)) | M3: =IF(A3="","",IF(K3<=0,"Sold Out","Active"))
I4: =IF(A4="","",SUMIFS(Expenses!D:D,Expenses!B:B,A4)) | J4: =IF(A4="","",SUMIFS(Sales!F:F,Sales!E:E,A4)) | K4: =IF(A4="","",F4-J4) | L4: =IF(A4="","",IF(F4=0,"",(E4*F4+I4)/F4)) | M4: =IF(A4="","",IF(K4<=0,"Sold Out","Active"))
I5: =IF(A5="","",SUMIFS(Expenses!D:D,Expenses!B:B,A5)) | J5: =IF(A5="","",SUMIFS(Sales!F:F,Sales!E:E,A5)) | K5: =IF(A5="","",F5-J5) | L5: =IF(A5="","",IF(F5=0,"",(E5*F5+I5)/F5)) | M5: =IF(A5="","",IF(K5<=0,"Sold Out","Active"))
I6: =IF(A6="","",SUMIFS(Expenses!D:D,Expenses!B:B,A6)) | J6: =IF(A6="","",SUMIFS(Sales!F:F,Sales!E:E,A6)) | K6: =IF(A6="","",F6-J6) | L6: =IF(A6="","",IF(F6=0,"",(E6*F6+I6)/F6)) | M6: =IF(A6="","",IF(K6<=0,"Sold Out","Active"))
I7: =IF(A7="","",SUMIFS(Expenses!D:D,Expenses!B:B,A7)) | J7: =IF(A7="","",SUMIFS(Sales!F:F,Sales!E:E,A7)) | K7: =IF(A7="","",F7-J7) | L7: =IF(A7="","",IF(F7=0,"",(E7*F7+I7)/F7)) | M7: =IF(A7="","",IF(K7<=0,"Sold Out","Active"))
I8: =IF(A8="","",SUMIFS(Expenses!D:D,Expenses!B:B,A8)) | J8: =IF(A8="","",SUMIFS(Sales!F:F,Sales!E:E,A8)) | K8: =IF(A8="","",F8-J8) | L8: =IF(A8="","",IF(F8=0,"",(E8*F8+I8)/F8)) | M8: =IF(A8="","",IF(K8<=0,"Sold Out","Active"))
I9: =IF(A9="","",SUMIFS(Expenses!D:D,Expenses!B:B,A9)) | J9: =IF(A9="","",SUMIFS(Sales!F:F,Sales!E:E,A9)) | K9: =IF(A9="","",F9-J9) | L9: =IF(A9="","",IF(F9=0,"",(E9*F9+I9)/F9)) | M9: =IF(A9="","",IF(K9<=0,"Sold Out","Active"))
I10: =IF(A10="","",SUMIFS(Expenses!D:D,Expenses!B:B,A10)) | J10: =IF(A10="","",SUMIFS(Sales!F:F,Sales!E:E,A10)) | K10: =IF(A10="","",F10-J10) | L10: =IF(A10="","",IF(F10=0,"",(E10*F10+I10)/F10)) | M10: =IF(A10="","",IF(K10<=0,"Sold Out","Active"))
I11: =IF(A11="","",SUMIFS(Expenses!D:D,Expenses!B:B,A11)) | J11: =IF(A11="","",SUMIFS(Sales!F:F,Sales!E:E,A11)) | K11: =IF(A11="","",F11-J11) | L11: =IF(A11="","",IF(F11=0,"",(E11*F11+I11)/F11)) | M11: =IF(A11="","",IF(K11<=0,"Sold Out","Active"))
I12: =IF(A12="","",SUMIFS(Expenses!D:D,Expenses!B:B,A12)) | J12: =IF(A12="","",SUMIFS(Sales!F:F,Sales!E:E,A12)) | K12: =IF(A12="","",F12-J12) | L12: =IF(A12="","",IF(F12=0,"",(E12*F12+I12)/F12)) | M12: =IF(A12="","",IF(K12<=0,"Sold Out","Active"))
I13: =IF(A13="","",SUMIFS(Expenses!D:D,Expenses!B:B,A13)) | J13: =IF(A13="","",SUMIFS(Sales!F:F,Sales!E:E,A13)) | K13: =IF(A13="","",F13-J13) | L13: =IF(A13="","",IF(F13=0,"",(E13*F13+I13)/F13)) | M13: =IF(A13="","",IF(K13<=0,"Sold Out","Active"))
... I501: =IF(A501="","",SUMIFS(Expenses!D:D,Expenses!B:B,A501)) | J501: =IF(A501="","",SUMIFS(Sales!F:F,Sales!E:E,A501)) | K501: =IF(A501="","",F501-J501) | L501: =IF(A501="","",IF(F501=0,"",(E501*F501+I501)/F501)) | M501: =IF(A501="","",IF(K501<=0,"Sold Out","Active"))

Sheet Sales
A1: Sale_ID | B1: Slice_No | C1: Sold_At | D1: Product_ID | E1: Lot_ID | F1: Qty | G1: Unit_Price | H1: Unit_Cost | I1: Payment | J1: Customer_Name | K1: Customer_Phone | L1: Total
L2: =IF(A2="","",F2*G2)
L3: =IF(A3="","",F3*G3)
L4: =IF(A4="","",F4*G4)
L5: =IF(A5="","",F5*G5)
L6: =IF(A6="","",F6*G6)
L7: =IF(A7="","",F7*G7)
L8: =IF(A8="","",F8*G8)
L9: =IF(A9="","",F9*G9)
L10: =IF(A10="","",F10*G10)
L11: =IF(A11="","",F11*G11)
L12: =IF(A12="","",F12*G12)
L13: =IF(A13="","",F13*G13)
... L501: =IF(A501="","",F501*G501)

Sheet Expenses
A1: Expense_ID | B1: Lot_ID | C1: Type | D1: Amount | E1: Date | F1: Note

Sheet Overhead
A1: Overhead_ID | B1: Month | C1: Type | D1: Amount | E1: Note

Sheet Quotes
A1: Quote_ID | B1: Created_At | C1: Customer_Name | D1: Customer_Phone | E1: Language | F1: Status | G1: Total | H1: Items_JSON

Sheet Stock
A1: Product_ID | B1: Product Name (English) | C1: Total Received | D1: Total Sold | E1: Remaining | F1: Last Sale Date | G1: Days Since Last Sale | H1: Stock Status
A2: =IF(Products!A2="","",Products!A2) | B2: =IF(A2="","",Products!C2) | C2: =IF(A2="","",SUMIFS(Lots!F:F,Lots!B:B,A2)) | D2: =IF(A2="","",SUMIFS(Sales!F:F,Sales!D:D,A2)) | E2: =IF(A2="","",C2-D2) | F2: =IF(A2="","",IF(D2=0,"",_xlfn.MAXIFS(Sales!C:C,Sales!D:D,A2))) | G2: =IF(A2="","",IF(F2="","",TODAY()-F2)) | H2: =IF(A2="","",IF(E2<=0,"Out of stock",IF(E2<=5,"Low stock",IF(AND(G2<>"",G2>=30),"Slow moving","OK"))))
A3: =IF(Products!A3="","",Products!A3) | B3: =IF(A3="","",Products!C3) | C3: =IF(A3="","",SUMIFS(Lots!F:F,Lots!B:B,A3)) | D3: =IF(A3="","",SUMIFS(Sales!F:F,Sales!D:D,A3)) | E3: =IF(A3="","",C3-D3) | F3: =IF(A3="","",IF(D3=0,"",_xlfn.MAXIFS(Sales!C:C,Sales!D:D,A3))) | G3: =IF(A3="","",IF(F3="","",TODAY()-F3)) | H3: =IF(A3="","",IF(E3<=0,"Out of stock",IF(E3<=5,"Low stock",IF(AND(G3<>"",G3>=30),"Slow moving","OK"))))
A4: =IF(Products!A4="","",Products!A4) | B4: =IF(A4="","",Products!C4) | C4: =IF(A4="","",SUMIFS(Lots!F:F,Lots!B:B,A4)) | D4: =IF(A4="","",SUMIFS(Sales!F:F,Sales!D:D,A4)) | E4: =IF(A4="","",C4-D4) | F4: =IF(A4="","",IF(D4=0,"",_xlfn.MAXIFS(Sales!C:C,Sales!D:D,A4))) | G4: =IF(A4="","",IF(F4="","",TODAY()-F4)) | H4: =IF(A4="","",IF(E4<=0,"Out of stock",IF(E4<=5,"Low stock",IF(AND(G4<>"",G4>=30),"Slow moving","OK"))))
A5: =IF(Products!A5="","",Products!A5) | B5: =IF(A5="","",Products!C5) | C5: =IF(A5="","",SUMIFS(Lots!F:F,Lots!B:B,A5)) | D5: =IF(A5="","",SUMIFS(Sales!F:F,Sales!D:D,A5)) | E5: =IF(A5="","",C5-D5) | F5: =IF(A5="","",IF(D5=0,"",_xlfn.MAXIFS(Sales!C:C,Sales!D:D,A5))) | G5: =IF(A5="","",IF(F5="","",TODAY()-F5)) | H5: =IF(A5="","",IF(E5<=0,"Out of stock",IF(E5<=5,"Low stock",IF(AND(G5<>"",G5>=30),"Slow moving","OK"))))
A6: =IF(Products!A6="","",Products!A6) | B6: =IF(A6="","",Products!C6) | C6: =IF(A6="","",SUMIFS(Lots!F:F,Lots!B:B,A6)) | D6: =IF(A6="","",SUMIFS(Sales!F:F,Sales!D:D,A6)) | E6: =IF(A6="","",C6-D6) | F6: =IF(A6="","",IF(D6=0,"",_xlfn.MAXIFS(Sales!C:C,Sales!D:D,A6))) | G6: =IF(A6="","",IF(F6="","",TODAY()-F6)) | H6: =IF(A6="","",IF(E6<=0,"Out of stock",IF(E6<=5,"Low stock",IF(AND(G6<>"",G6>=30),"Slow moving","OK"))))
A7: =IF(Products!A7="","",Products!A7) | B7: =IF(A7="","",Products!C7) | C7: =IF(A7="","",SUMIFS(Lots!F:F,Lots!B:B,A7)) | D7: =IF(A7="","",SUMIFS(Sales!F:F,Sales!D:D,A7)) | E7: =IF(A7="","",C7-D7) | F7: =IF(A7="","",IF(D7=0,"",_xlfn.MAXIFS(Sales!C:C,Sales!D:D,A7))) | G7: =IF(A7="","",IF(F7="","",TODAY()-F7)) | H7: =IF(A7="","",IF(E7<=0,"Out of stock",IF(E7<=5,"Low stock",IF(AND(G7<>"",G7>=30),"Slow moving","OK"))))
A8: =IF(Products!A8="","",Products!A8) | B8: =IF(A8="","",Products!C8) | C8: =IF(A8="","",SUMIFS(Lots!F:F,Lots!B:B,A8)) | D8: =IF(A8="","",SUMIFS(Sales!F:F,Sales!D:D,A8)) | E8: =IF(A8="","",C8-D8) | F8: =IF(A8="","",IF(D8=0,"",_xlfn.MAXIFS(Sales!C:C,Sales!D:D,A8))) | G8: =IF(A8="","",IF(F8="","",TODAY()-F8)) | H8: =IF(A8="","",IF(E8<=0,"Out of stock",IF(E8<=5,"Low stock",IF(AND(G8<>"",G8>=30),"Slow moving","OK"))))
A9: =IF(Products!A9="","",Products!A9) | B9: =IF(A9="","",Products!C9) | C9: =IF(A9="","",SUMIFS(Lots!F:F,Lots!B:B,A9)) | D9: =IF(A9="","",SUMIFS(Sales!F:F,Sales!D:D,A9)) | E9: =IF(A9="","",C9-D9) | F9: =IF(A9="","",IF(D9=0,"",_xlfn.MAXIFS(Sales!C:C,Sales!D:D,A9))) | G9: =IF(A9="","",IF(F9="","",TODAY()-F9)) | H9: =IF(A9="","",IF(E9<=0,"Out of stock",IF(E9<=5,"Low stock",IF(AND(G9<>"",G9>=30),"Slow moving","OK"))))
A10: =IF(Products!A10="","",Products!A10) | B10: =IF(A10="","",Products!C10) | C10: =IF(A10="","",SUMIFS(Lots!F:F,Lots!B:B,A10)) | D10: =IF(A10="","",SUMIFS(Sales!F:F,Sales!D:D,A10)) | E10: =IF(A10="","",C10-D10) | F10: =IF(A10="","",IF(D10=0,"",_xlfn.MAXIFS(Sales!C:C,Sales!D:D,A10))) | G10: =IF(A10="","",IF(F10="","",TODAY()-F10)) | H10: =IF(A10="","",IF(E10<=0,"Out of stock",IF(E10<=5,"Low stock",IF(AND(G10<>"",G10>=30),"Slow moving","OK"))))
A11: =IF(Products!A11="","",Products!A11) | B11: =IF(A11="","",Products!C11) | C11: =IF(A11="","",SUMIFS(Lots!F:F,Lots!B:B,A11)) | D11: =IF(A11="","",SUMIFS(Sales!F:F,Sales!D:D,A11)) | E11: =IF(A11="","",C11-D11) | F11: =IF(A11="","",IF(D11=0,"",_xlfn.MAXIFS(Sales!C:C,Sales!D:D,A11))) | G11: =IF(A11="","",IF(F11="","",TODAY()-F11)) | H11: =IF(A11="","",IF(E11<=0,"Out of stock",IF(E11<=5,"Low stock",IF(AND(G11<>"",G11>=30),"Slow moving","OK"))))
A12: =IF(Products!A12="","",Products!A12) | B12: =IF(A12="","",Products!C12) | C12: =IF(A12="","",SUMIFS(Lots!F:F,Lots!B:B,A12)) | D12: =IF(A12="","",SUMIFS(Sales!F:F,Sales!D:D,A12)) | E12: =IF(A12="","",C12-D12) | F12: =IF(A12="","",IF(D12=0,"",_xlfn.MAXIFS(Sales!C:C,Sales!D:D,A12))) | G12: =IF(A12="","",IF(F12="","",TODAY()-F12)) | H12: =IF(A12="","",IF(E12<=0,"Out of stock",IF(E12<=5,"Low stock",IF(AND(G12<>"",G12>=30),"Slow moving","OK"))))
A13: =IF(Products!A13="","",Products!A13) | B13: =IF(A13="","",Products!C13) | C13: =IF(A13="","",SUMIFS(Lots!F:F,Lots!B:B,A13)) | D13: =IF(A13="","",SUMIFS(Sales!F:F,Sales!D:D,A13)) | E13: =IF(A13="","",C13-D13) | F13: =IF(A13="","",IF(D13=0,"",_xlfn.MAXIFS(Sales!C:C,Sales!D:D,A13))) | G13: =IF(A13="","",IF(F13="","",TODAY()-F13)) | H13: =IF(A13="","",IF(E13<=0,"Out of stock",IF(E13<=5,"Low stock",IF(AND(G13<>"",G13>=30),"Slow moving","OK"))))
... A501: =IF(Products!A501="","",Products!A501) | B501: =IF(A501="","",Products!C501) | C501: =IF(A501="","",SUMIFS(Lots!F:F,Lots!B:B,A501)) | D501: =IF(A501="","",SUMIFS(Sales!F:F,Sales!D:D,A501)) | E501: =IF(A501="","",C501-D501) | F501: =IF(A501="","",IF(D501=0,"",_xlfn.MAXIFS(Sales!C:C,Sales!D:D,A501))) | G501: =IF(A501="","",IF(F501="","",TODAY()-F501)) | H501: =IF(A501="","",IF(E501<=0,"Out of stock",IF(E501<=5,"Low stock",IF(AND(G501<>"",G501>=30),"Slow moving","OK"))))
